real_robot/__init__.py
real_robot/agents/__init__.py
real_robot/agents/xarm.py
real_robot/assets/descriptions/xarm7.srdf
real_robot/assets/descriptions/xarm7.urdf
real_robot/assets/descriptions/xarm7_d435.urdf
real_robot/assets/descriptions/xarm7_d435_orig.urdf
real_robot/assets/descriptions/xarm7_orig.srdf
real_robot/assets/descriptions/xarm7_orig.urdf
real_robot/assets/descriptions/xarm7_pris_finger.srdf
real_robot/assets/descriptions/xarm7_pris_finger.urdf
real_robot/assets/descriptions/xarm7_pris_finger_d435.urdf
real_robot/assets/descriptions/xarm_floating_pris_finger.urdf
real_robot/assets/descriptions/xarm_floating_pris_finger_d435.urdf
real_robot/assets/descriptions/xarm_description/meshes/camera/realsense/collision/d435_with_cam_stand.STL
real_robot/assets/descriptions/xarm_description/meshes/camera/realsense/collision/d435_with_tilt_cam_stand.STL
real_robot/assets/descriptions/xarm_description/meshes/camera/realsense/visual/d435_with_cam_stand.STL
real_robot/assets/descriptions/xarm_description/meshes/camera/realsense/visual/d435_with_tilt_cam_stand.STL
real_robot/assets/descriptions/xarm_description/meshes/camera/realsense/visual/d435_with_tilt_cam_stand.glb
real_robot/assets/descriptions/xarm_description/meshes/end_tool/collision/end_tool.STL
real_robot/assets/descriptions/xarm_description/meshes/gripper/xarm/base_link.STL
real_robot/assets/descriptions/xarm_description/meshes/gripper/xarm/base_link_collision.STL
real_robot/assets/descriptions/xarm_description/meshes/gripper/xarm/left_finger.STL
real_robot/assets/descriptions/xarm_description/meshes/gripper/xarm/left_finger_black.glb
real_robot/assets/descriptions/xarm_description/meshes/gripper/xarm/left_inner_knuckle.STL
real_robot/assets/descriptions/xarm_description/meshes/gripper/xarm/left_inner_knuckle_black.glb
real_robot/assets/descriptions/xarm_description/meshes/gripper/xarm/left_outer_knuckle.STL
real_robot/assets/descriptions/xarm_description/meshes/gripper/xarm/left_outer_knuckle_black.glb
real_robot-0.2.1.dist-info/licenses/LICENSE
real_robot-0.2.1.dist-info/METADATA
real_robot-0.2.1.dist-info/WHEEL
real_robot-0.2.1.dist-info/top_level.txt
real_robot-0.2.1.dist-info/RECORD
