Metadata-Version: 2.4
Name: real_robot
Version: 0.2.1
Summary: Real robot interface and utilities for asynchronous real-time deployment.
Author-email: Kolin Guo <guokolin@gmail.com>
License-Expression: MIT
Project-URL: Repository, https://github.com/KolinGuo/RealRobot
Keywords: robotics,sensor,visualization,control
Classifier: Development Status :: 3 - Alpha
Classifier: Operating System :: POSIX :: Linux
Classifier: Intended Audience :: Developers
Classifier: Intended Audience :: Education
Classifier: Intended Audience :: Other Audience
Classifier: Intended Audience :: Science/Research
Classifier: Natural Language :: English
Classifier: Framework :: Robot Framework :: Library
Classifier: Framework :: Robot Framework :: Tool
Classifier: Programming Language :: Python :: 3.9
Classifier: Programming Language :: Python :: 3.10
Classifier: Programming Language :: Python :: 3.11
Classifier: Programming Language :: Python :: 3.12
Classifier: Programming Language :: Python :: 3.13
Classifier: Topic :: Education
Classifier: Topic :: Software Development :: Libraries :: Python Modules
Classifier: Topic :: Scientific/Engineering
Classifier: Topic :: Utilities
Requires-Python: >=3.10
License-File: LICENSE
Requires-Dist: numpy
Requires-Dist: loguru>=0.7.3
Provides-Extra: vis
Requires-Dist: opencv-python; extra == "vis"
Requires-Dist: Pillow; extra == "vis"
Requires-Dist: scipy>=1.10.0; extra == "vis"
Requires-Dist: open3d>=0.17.0; extra == "vis"
Requires-Dist: pynput; extra == "vis"
Provides-Extra: vis-all
Requires-Dist: real_robot[vis]; extra == "vis-all"
Requires-Dist: urchin; extra == "vis-all"
Provides-Extra: all
Requires-Dist: real_robot[vis_all]; extra == "all"
Requires-Dist: pyrealsense2==2.54.2.5684; extra == "all"
Requires-Dist: gymnasium; extra == "all"
Requires-Dist: transforms3d; extra == "all"
Requires-Dist: opencv-contrib-python; extra == "all"
Requires-Dist: sapien~=3.0.0.dev; extra == "all"
Dynamic: license-file
